.gitignore
LICENSE
README.en.md
README.md
setup.py
.idea/.gitignore
.idea/lml_python.iml
.idea/misc.xml
.idea/modules.xml
.idea/vcs.xml
.idea/inspectionProfiles/Project_Default.xml
.idea/inspectionProfiles/profiles_settings.xml
lml/__init__.py
lml/t1.py
lml_python.egg-info/PKG-INFO
lml_python.egg-info/SOURCES.txt
lml_python.egg-info/dependency_links.txt
lml_python.egg-info/top_level.txt