Metadata-Version: 2.1
Name: lml-python
Version: 1.0.1
Summary: ['lml-python', 'lml-py']
Home-page: https://github.com/122809690/lml_python
Author: lml
Author-email: 122809690@qq.com
License: MIT
Keywords: ct
Platform: UNKNOWN
Requires-Python: >=3.7
License-File: LICENSE
